MANIFEST.in
README
setup.py
site.cfg.template
csc_pysparse.egg-info/PKG-INFO
csc_pysparse.egg-info/SOURCES.txt
csc_pysparse.egg-info/dependency_links.txt
csc_pysparse.egg-info/top_level.txt
doc/pysparse/source/conf.py
doc/pysparse/source/contents.rst
doc/pysparse/source/fact.rst
doc/pysparse/source/formats.rst
doc/pysparse/source/introduction.rst
doc/pysparse/source/itsolvers.rst
doc/pysparse/source/jdsym.rst
doc/pysparse/source/license.rst
doc/pysparse/source/logo.py
doc/pysparse/source/other.rst
doc/pysparse/source/precon.rst
doc/pysparse/source/pysparsematrix.rst
doc/pysparse/source/spmatrix-logo-large.png
doc/pysparse/source/spmatrix-logo.eps
doc/pysparse/source/spmatrix-logo.pdf
doc/pysparse/source/spmatrix-logo.png
doc/pysparse/source/spmatrix.rst
doc/pysparse/source/.static/default.css
doc/pysparse/source/.static/pysparse.css
doc/pysparse/source/.static/rightsidebar.css
doc/pysparse/source/.static/sphinxdoc.css
doc/pysparse/source/.static/stickysidebar.css
doc/pysparse/source/.static/traditional.css
doc/pysparse/source/.templates/index.html
doc/pysparse/source/.templates/indexsidebar.html
doc/pysparse/source/.templates/layout.html
doc/pysparse/source/sphinxext/ipython_console_highlighting.py
doc/pysparse/source/sphinxext/readme
examples/jdsym_debug.py
examples/jdsym_demo.py
examples/jdsym_test.py
examples/matmul_perftest.py
examples/poisson2dvec.py
examples/poisson_gmres.py
examples/poisson_test.py
examples/poisson_test_eig.py
examples/pysparse_test.py
examples/sortedLL_test.py
examples/spmatrix_test.py
examples/ssor_test.py
examples/tendigit.py
examples/umftest.py
pysparse/__init__.py
pysparse/setup.py
pysparse/version.py
pysparse/direct/__init__.py
pysparse/direct/directSolver.py
pysparse/direct/pysparseSuperLU.py
pysparse/direct/pysparseUmfpack.py
pysparse/direct/setup.py
pysparse/direct/amd/include/amd.h
pysparse/direct/amd/include/amd_internal.h
pysparse/direct/amd/src/amd_1.c
pysparse/direct/amd/src/amd_2.c
pysparse/direct/amd/src/amd_aat.c
pysparse/direct/amd/src/amd_control.c
pysparse/direct/amd/src/amd_defaults.c
pysparse/direct/amd/src/amd_dump.c
pysparse/direct/amd/src/amd_info.c
