Metadata-Version: 1.0
Name: csc-pysparse
Version: 1.1.1.1
Summary: A fast sparse matrix library for Python (Commonsense Computing version)
Home-page: http://github.com/rspeer/csc-pysparse
Author: Rob Speer
Author-email: rspeer@mit.edu
License: BSD-style
Platform: Windows
Platform: Linux
Platform: Solaris
Platform: Mac OS-X
Platform: Unix
Classifier: Development Status :: 4 - Beta
Classifier: Intended Audience :: Science/Research
Classifier: Intended Audience :: Developers
Classifier: License :: OSI Approved :: BSD License
Classifier: Programming Language :: Python
Classifier: Programming Language :: C
Classifier: Topic :: Software Development
Classifier: Topic :: Scientific/Engineering
Classifier: Operating System :: Microsoft :: Windows
Classifier: Operating System :: POSIX
Classifier: Operating System :: Unix
Classifier: Operating System :: MacOS
